data/.gitkeep
data/README.md
data/conj.csv
data/conjo.csv
data/kwpos.csv
himotoki/__init__.py
himotoki/__main__.py
himotoki/characters.py
himotoki/cli.py
himotoki/conjugation_hints.py
himotoki/constants.py
himotoki/counters.py
himotoki/lookup.py
himotoki/output.py
himotoki/raw_types.py
himotoki/segment.py
himotoki/setup.py
himotoki/splits.py
himotoki/suffixes.py
himotoki/synergies.py
himotoki/trie.py
himotoki/db/__init__.py
himotoki/db/connection.py
himotoki/db/models.py
himotoki/loading/__init__.py
himotoki/loading/conjugations.py
himotoki/loading/errata.py
himotoki/loading/jmdict.py
himotoki-0.2.3.dist-info/licenses/LICENSE
himotoki-0.2.3.dist-info/METADATA
himotoki-0.2.3.dist-info/WHEEL
himotoki-0.2.3.dist-info/entry_points.txt
himotoki-0.2.3.dist-info/top_level.txt
himotoki-0.2.3.dist-info/RECORD
