Metadata-Version: 2.4
Name: himotoki
Version: 0.2.3
Summary: Japanese Morphological Analyzer and Romanization tool - Python remake of ichiran
Author: Himotoki Contributors
License-Expression: MIT
Project-URL: Homepage, https://github.com/msr2903/himotoki
Project-URL: Documentation, https://github.com/msr2903/himotoki#readme
Project-URL: Repository, https://github.com/msr2903/himotoki
Project-URL: Issues, https://github.com/msr2903/himotoki/issues
Keywords: japanese,nlp,morphological-analysis,dictionary,jmdict
Classifier: Development Status :: 4 - Beta
Classifier: Intended Audience :: Developers
Classifier: Intended Audience :: Science/Research
Classifier: Operating System :: OS Independent
Classifier: Programming Language :: Python :: 3
Classifier: Programming Language :: Python :: 3.10
Classifier: Programming Language :: Python :: 3.11
Classifier: Programming Language :: Python :: 3.12
Classifier: Programming Language :: Python :: 3.13
Classifier: Topic :: Text Processing :: Linguistic
Classifier: Topic :: Software Development :: Libraries :: Python Modules
Classifier: Topic :: Scientific/Engineering :: Artificial Intelligence
Classifier: Natural Language :: Japanese
Requires-Python: >=3.10
License-File: LICENSE
Requires-Dist: sqlalchemy>=2.0.0
Requires-Dist: lxml>=4.9.0
Requires-Dist: marisa-trie>=1.0.0
Provides-Extra: dev
Requires-Dist: pytest>=7.0.0; extra == "dev"
Requires-Dist: pytest-cov>=4.0.0; extra == "dev"
Requires-Dist: hypothesis>=6.0.0; extra == "dev"
Requires-Dist: black>=23.0.0; extra == "dev"
Requires-Dist: isort>=5.12.0; extra == "dev"
Requires-Dist: mypy>=1.0.0; extra == "dev"
Dynamic: license-file
